commonkit/__init__.py
commonkit/django/db/fields.py
commonkit/django/models.py
commonkit/private/__init__.py
commonkit/private/errors.py
commonkit/private/loggers.py
commonkit/private/utils.py
commonkit/rest_framework/pandas/__init__.py
commonkit/rest_framework/polars/__init__.py
commonkit/rest_framework/renderers.py
commonkit/rest_framework/serializers.py
commonkit/rest_framework/viewsets.py
commonkit/utils.py
commonkit-1.0.8.dist-info/LICENSE.txt
commonkit-1.0.8.dist-info/METADATA
commonkit-1.0.8.dist-info/WHEEL
commonkit-1.0.8.dist-info/RECORD
