Metadata-Version: 2.1
Name: commonkit
Version: 1.0.8
Summary: A library for handling common stuff in Python
License: MIT
Author: leondaz
Author-email: ahmeddark369@gmail.com
Requires-Python: >=3.9,<4.0
Classifier: License :: OSI Approved :: MIT License
Classifier: Programming Language :: Python :: 3
Classifier: Programming Language :: Python :: 3.9
Classifier: Programming Language :: Python :: 3.10
Classifier: Programming Language :: Python :: 3.11
Classifier: Programming Language :: Python :: 3.12
Requires-Dist: django (>=4.2.7,<5.0.0)
Requires-Dist: djangorestframework (>=3.14.0,<4.0.0)
